pyobjson/__init__.py
pyobjson/base.py
pyobjson/constants.py
pyobjson/data.py
pyobjson/utils.py
pyobjson/dao/__init__.py
pyobjson/dao/mongo/__init__.py
pyobjson/dao/mongo/base.py
pyobjson-6.2.1.dist-info/METADATA
pyobjson-6.2.1.dist-info/WHEEL
pyobjson-6.2.1.dist-info/licenses/LICENSE
pyobjson-6.2.1.dist-info/RECORD
