Metadata-Version: 2.4
Name: pyobjson
Version: 6.2.1
Summary: Utility library for serializing/deserializing custom Python objects to/from JSON.
Project-URL: Homepage, https://github.com/wrencode/pyobjson
Project-URL: Issues, https://github.com/wrencode/pyobjson/issues
Author-email: "Wren J. Rudolph for Wrencode, LLC" <dev@wrencode.com>
License: MIT
License-File: LICENSE
Classifier: License :: OSI Approved :: MIT License
Classifier: Operating System :: OS Independent
Classifier: Programming Language :: Python :: 3
Classifier: Programming Language :: Python :: 3.9
Classifier: Programming Language :: Python :: 3.10
Classifier: Programming Language :: Python :: 3.11
Classifier: Programming Language :: Python :: 3.12
Classifier: Programming Language :: Python :: 3.13
Requires-Python: >=3.9
Provides-Extra: mongo
Requires-Dist: pymongo>=4.10.1; extra == 'mongo'
